LICENSE
MANIFEST.in
README.rst
setup.py
django_forms_smoq.egg-info/PKG-INFO
django_forms_smoq.egg-info/SOURCES.txt
django_forms_smoq.egg-info/dependency_links.txt
django_forms_smoq.egg-info/top_level.txt
forms_smoq/__init__.py
forms_smoq/forms.py
forms_smoq/tests.py