Metadata-Version: 1.1
Name: django-forms-smoq
Version: 0.1
Summary: Forms-SmoQ django is a simple application that contains useful forms for use in django.
Home-page: https://github.com/SmoQ/django-forms-smoq
Author: Mariusz Sobczak
Author-email: mariuszsobczak87@gmail.com
License: BSD License
Platform: UNKNOWN
Classifier: Environment :: Web Environment
Classifier: Framework :: Django
Classifier: Intended Audience :: Developers
Classifier: License :: OSI Approved :: BSD License
Classifier: Operating System :: OS Independent
Classifier: Programming Language :: Python
Classifier: Programming Language :: Python :: 2.6
Classifier: Programming Language :: Python :: 2.7
Classifier: Programming Language :: Python :: 3.3
Classifier: Topic :: Internet :: WWW/HTTP
Classifier: Topic :: Internet :: WWW/HTTP :: Dynamic Content
